{
  "name": "Pickaxe",
  "category": "tools/tool_types",
  "icon": "essence:essence_crystal",
  "pages": [
    {
      "type": "text",
      "text": "lorem ipsum dolar banana"
    },
    {
      "type": "crafting",
      "recipe": "essence:essence_pickaxe_basic",
      "text": "",
      "advancement": ""
    },
    {
      "type": "crafting",
      "recipe": "essence:essence_pickaxe_empowered",
      "text": "",
      "advancement": ""
    },
    {
      "type": "crafting",
      "recipe": "essence:essence_pickaxe_exalted",
      "text": "",
      "advancement": ""
    },
    {
      "type": "crafting",
      "recipe": "essence:essence_pickaxe_godly",
      "text": "",
      "advancement": ""
    }
  ],
  "sortnum": 4,
  "secret": "true"
}